python_canvas_layer/__init__.py
python_canvas_layer/canvas_status.py
python_canvas_layer/course_info.py
python_canvas_layer/pycanvas.py
python_canvas_layer-0.0.3.dist-info/LICENSE
python_canvas_layer-0.0.3.dist-info/METADATA
python_canvas_layer-0.0.3.dist-info/WHEEL
python_canvas_layer-0.0.3.dist-info/top_level.txt
python_canvas_layer-0.0.3.dist-info/RECORD
