Metadata-Version: 2.1
Name: python_canvas_layer
Version: 0.0.3
Summary: A lightweight Python layer over the Canvas LMS API
Author-email: Zack Ives <zives@cis.upenn.edu>
Project-URL: Homepage, https://github.com/upenn/python_canvas
Project-URL: Issues, https://github.com/upenn/python_canvas/issues
Classifier: Programming Language :: Python :: 3
Classifier: License :: OSI Approved :: Apache Software License
Classifier: Operating System :: OS Independent
Requires-Python: >=3.9
License-File: LICENSE
Requires-Dist: requests
Requires-Dist: html5lib
Requires-Dist: beautifulsoup4
Requires-Dist: canvasapi
Requires-Dist: pandas
Requires-Dist: pytz
Requires-Dist: pyyaml
